setup.py
tornado_async_odm/__init__.py
tornado_async_odm/dbclient.py
tornado_async_odm/errors.py
tornado_async_odm/structures.py
tornado_async_odm.egg-info/PKG-INFO
tornado_async_odm.egg-info/SOURCES.txt
tornado_async_odm.egg-info/dependency_links.txt
tornado_async_odm.egg-info/not-zip-safe
tornado_async_odm.egg-info/requires.txt
tornado_async_odm.egg-info/top_level.txt