Metadata-Version: 1.1
Name: tornado-async-odm
Version: 1.0.0
Summary: Asynchronous Object Document Mapper designed for Tornado Web Server
Home-page: https://github.com/shicky/tornado_async_odm
Author: Sick Yoon
Author-email: shicky@gmail.com
License: MIT
Download-URL: https://github.com/shicky/tornado_async_odm/tarball/v1.0.0
Keywords: webserver,tornado,flask,orm,odm,database
Platform: UNKNOWN
Classifier: Development Status :: 3 - Alpha
Classifier: Intended Audience :: Developers
Classifier: License :: OSI Approved :: MIT License
Classifier: Natural Language :: English
Classifier: Operating System :: OS Independent
Classifier: Programming Language :: Python :: 3
Classifier: Topic :: Software Development :: Libraries :: Application Frameworks
